amazon_connect_decryption_lib/__init__.py
amazon_connect_decryption_lib/core.py
amazon_connect_decryption_lib/shortcut.py
tests/__init__.py
tests/test_unit.py
amazon_connect_decryption_lib-0.2.0.dist-info/LICENSE
amazon_connect_decryption_lib-0.2.0.dist-info/METADATA
amazon_connect_decryption_lib-0.2.0.dist-info/WHEEL
amazon_connect_decryption_lib-0.2.0.dist-info/top_level.txt
amazon_connect_decryption_lib-0.2.0.dist-info/RECORD
