Metadata-Version: 2.1
Name: amazon-connect-decryption-lib
Version: 0.2.0
Summary: Amazon Connect Decryption Library for Python
Home-page: https://github.com/shinsaka/amazon-connect-decryption-lib
Author: shinsaka
Author-email: shinx1265@gmail.com
Maintainer: shinsaka
Maintainer-email: shinx1265@gmail.com
License: MIT
Platform: UNKNOWN
Classifier: Programming Language :: Python :: 3.8
Classifier: License :: OSI Approved :: MIT License
Requires-Dist: aws-encryption-sdk (>=2.0.0)
Requires-Dist: boto3 (>=1.15.16)
